tornado_elastic2/__init__.py
tornado_elastic2/utils.py
tornado_elastic2-0.0.2.dist-info/METADATA
tornado_elastic2-0.0.2.dist-info/WHEEL
tornado_elastic2-0.0.2.dist-info/top_level.txt
tornado_elastic2-0.0.2.dist-info/RECORD
